{
  "id": "countrystatecity",
  "protocol_version": "0.2.0",
  "identity": {
    "name": "CountryStateCity",
    "purpose": "World countries, states, regions, provinces, cities & towns in JSON, SQL, XML, YAML, & CSV format"
  },
  "offers": [
    {
      "intent": "use_api",
      "description": "가상의 기본 엔드포인트: https://countrystatecity.in/",
      "endpoint": "/",
      "method": "GET",
      "side_effect": "read-only",
      "auth_type": "api_key",
      "confidence_score": 0.5
    }
  ],
  "needs": [
    {
      "intent": "identity.api_key",
      "criticality": "required"
    }
  ]
}