{
  "id": "lidar",
  "protocol_version": "0.2.0",
  "identity": {
    "name": "LIDAR",
    "purpose": "Sensor for measuring distances by illuminating the target with laser light."
  },
  "offers": [
    {
      "intent": "use_api",
      "description": "가상의 기본 엔드포인트: https://github.com/szenergy/awesome-lidar#readme",
      "endpoint": "/",
      "method": "GET",
      "side_effect": "read-only",
      "auth_type": "api_key",
      "confidence_score": 0.5
    }
  ],
  "needs": [
    {
      "intent": "identity.api_key",
      "criticality": "required"
    }
  ]
}