{
  "id": "ml-with-ruby",
  "protocol_version": "0.2.0",
  "identity": {
    "name": "ML with Ruby",
    "purpose": "Learning, implementing, and applying Machine Learning using Ruby."
  },
  "offers": [
    {
      "intent": "use_api",
      "description": "가상의 기본 엔드포인트: https://github.com/arbox/machine-learning-with-ruby#readme",
      "endpoint": "/",
      "method": "GET",
      "side_effect": "read-only",
      "auth_type": "api_key",
      "confidence_score": 0.5
    }
  ],
  "needs": [
    {
      "intent": "identity.api_key",
      "criticality": "required"
    }
  ]
}