{
  "id": "quickmocker",
  "protocol_version": "0.2.0",
  "identity": {
    "name": "QuickMocker",
    "purpose": "API mocking tool to generate contextual, fake or random data"
  },
  "offers": [
    {
      "intent": "use_api",
      "description": "가상의 기본 엔드포인트: https://quickmocker.com",
      "endpoint": "/",
      "method": "GET",
      "side_effect": "read-only",
      "auth_type": "api_key",
      "confidence_score": 0.5
    }
  ],
  "needs": [
    {
      "intent": "identity.api_key",
      "criticality": "required"
    }
  ]
}